datachoices/__init__.py
datachoices/choices.py
datachoices/fields.py
django_datachoices-0.1.3.dist-info/licenses/LICENSE
django_datachoices-0.1.3.dist-info/METADATA
django_datachoices-0.1.3.dist-info/WHEEL
django_datachoices-0.1.3.dist-info/top_level.txt
django_datachoices-0.1.3.dist-info/RECORD
