Metadata-Version: 2.4
Name: django-datachoices
Version: 0.1.3
Summary: A utility for Django to bind complex data to field choices.
Author: blu14x
License: MIT License
Project-URL: Homepage, https://github.com/blu14x/django-datachoices
Project-URL: Issues, https://github.com/blu14x/django-datachoices/issues
Classifier: Topic :: Utilities
Classifier: Framework :: Django
Classifier: Programming Language :: Python :: 3
Requires-Python: >=3.6
License-File: LICENSE
Dynamic: license-file
